{
    "web":{
        "client_id":"18018405840-m860p813kjpl233au0ub3iime16t2lg9.apps.googleusercontent.com",
        "project_id":"fairshare-445419",
        "auth_uri":"https://accounts.google.com/o/oauth2/auth",
        "token_uri":"https://oauth2.googleapis.com/token",
        "auth_provider_x509_cert_url":"https://www.googleapis.com/oauth2/v1/certs",
        "client_secret":"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",
        "redirect_uris":["http://127.0.0.1:8000/","http://127.0.0.1:8000/accounts/google/login/callback"
        ]
    }
}